krippendorff/__init__.py
krippendorff/krippendorff.py
krippendorff-0.8.0.dist-info/LICENSE.txt
krippendorff-0.8.0.dist-info/METADATA
krippendorff-0.8.0.dist-info/WHEEL
krippendorff-0.8.0.dist-info/RECORD
