Metadata-Version: 2.1
Name: krippendorff
Version: 0.8.0
Summary: Fast computation of the Krippendorff's alpha measure.
Home-page: https://github.com/pln-fing-udelar/fast-krippendorff
License: GPL-3.0-or-later
Keywords: Krippendorff,alpha,agreement,reliability,coding,coders,units,values
Author: Santiago Castro
Author-email: sacastro@fing.edu.uy
Requires-Python: >=3.9,<4.0
Classifier: Development Status :: 4 - Beta
Classifier: Intended Audience :: Science/Research
Classifier: License :: OSI Approved :: GNU General Public License v3 (GPLv3)
Classifier: License :: OSI Approved :: GNU General Public License v3 or later (GPLv3+)
Classifier: Operating System :: OS Independent
Classifier: Programming Language :: Python
Classifier: Programming Language :: Python :: 3
Classifier: Programming Language :: Python :: 3.9
Classifier: Programming Language :: Python :: 3.10
Classifier: Programming Language :: Python :: 3.11
Classifier: Programming Language :: Python :: 3.12
Classifier: Programming Language :: Python :: 3.13
Classifier: Topic :: Scientific/Engineering
Classifier: Topic :: Scientific/Engineering :: Artificial Intelligence
Requires-Dist: numpy (>=1.21)
Project-URL: Repository, https://github.com/pln-fing-udelar/fast-krippendorff
